[{
  "_id": {
    "$oid": "68af8920987317c91f8fdad6"
  },
  "titulo": "Perfect Days",
  "anio": 2023,
  "generos": [
    "Drama"
  ],
  "pais": "Japón",
  "duracionMin": 125,
  "rating": 7.9,
  "director": "Wim Wenders",
  "reparto": [
    "Kōji Yakusho",
    "Tokio Emoto"
  ],
  "plataformas": [
    "MUBI"
  ],
  "apta": "ATP",
  "taquillaUSD": 35400000,
  "destacada": true
},
{
  "_id": {
    "$oid": "68af8920987317c91f8fdad7"
  },
  "titulo": "Parasite",
  "anio": 2019,
  "generos": [
    "Drama",
    "Thriller"
  ],
  "pais": "Corea del Sur",
  "duracionMin": 132,
  "rating": 8.5,
  "director": "Bong Joon-ho",
  "reparto": [
    "Song Kang-ho",
    "Choi Woo-shik",
    "Park So-dam"
  ],
  "plataformas": [
    "Prime Video"
  ],
  "apta": "16+",
  "taquillaUSD": 263000000,
  "destacada": true
},
{
  "_id": {
    "$oid": "68af8920987317c91f8fdad8"
  },
  "titulo": "Whiplash",
  "anio": 2014,
  "generos": [
    "Drama",
    "Música"
  ],
  "pais": "Estados Unidos",
  "duracionMin": 106,
  "rating": 8.5,
  "director": "Damien Chazelle",
  "reparto": [
    "Miles Teller",
    "J. K. Simmons"
  ],
  "plataformas": [
    "HBO Max"
  ],
  "apta": "16+",
  "taquillaUSD": 49000000,
  "destacada": false
},
{
  "_id": {
    "$oid": "68af8920987317c91f8fdad9"
  },
  "titulo": "Spirited Away",
  "anio": 2001,
  "generos": [
    "Animación",
    "Fantasía"
  ],
  "pais": "Japón",
  "duracionMin": 125,
  "rating": 8.6,
  "director": "Hayao Miyazaki",
  "reparto": [
    "Rumi Hiiragi",
    "Miyu Irino"
  ],
  "plataformas": [
    "Netflix"
  ],
  "apta": "ATP",
  "taquillaUSD": 395800000,
  "destacada": true
},
{
  "_id": {
    "$oid": "68af8920987317c91f8fdada"
  },
  "titulo": "The Social Network",
  "anio": 2010,
  "generos": [
    "Drama",
    "Biografía"
  ],
  "pais": "Estados Unidos",
  "duracionMin": 120,
  "rating": 7.8,
  "director": "David Fincher",
  "reparto": [
    "Jesse Eisenberg",
    "Andrew Garfield",
    "Rooney Mara"
  ],
  "plataformas": [
    "Netflix"
  ],
  "apta": "13+",
  "taquillaUSD": 224900000,
  "destacada": false
}]